si_person_maker/__init__.py
si_person_maker/data.py
si_person_maker/person.py
si_person_maker-0.0.1.dist-info/METADATA
si_person_maker-0.0.1.dist-info/WHEEL
si_person_maker-0.0.1.dist-info/licenses/LICENSE
si_person_maker-0.0.1.dist-info/RECORD
