Metadata-Version: 2.1
Name: si_person_maker
Version: 0.0.1
Summary: Will make random person object with Slovenian names, last names, addresses etc.
Project-URL: Homepage,  https://github.com/NoFakMiha/si_person_object_maker
Author-email: Miha Novak <miha.novak@outlook.de>
License: Copyright (c) 2018 The Python Packaging Authority
Keywords: data,object,random
Classifier: License :: OSI Approved :: MIT License
Classifier: Programming Language :: Python
Classifier: Programming Language :: Python :: 3
Provides-Extra: dev
Requires-Dist: pytest; extra == 'dev'
